{"id":"d3255eeb-9042-45b0-bad1-a44efbeb83b7","title":"The Manager’s Path by Camille Fournier: 9 Minute Summary","type":"url","properties":{"url":"https://www.youtube.com/watch?v=O-AMMiPSWmk","hostname":"www.youtube.com","thumbnail":"https://i.ytimg.com/vi/O-AMMiPSWmk/maxresdefault.jpg","contentType":"media+video","platform":"youtube"},"tags":["book","watch-later","career","engineering-manager"],"description":"*BOOK SUMMARY*TITLE - The Manager’s Path: A Guide for Tech Leaders Navigating Growth and ChangeAUTHOR - Camille FournierDESCRIPTION:📖 Looking to up your man…","createdAt":1732933558608,"updatedAt":1732933558608}