{"id":"e5d002e5-dbfb-4980-aeb5-bf97d635a40e","title":"How to Organise your Life - Building a Second Brain","type":"url","properties":{"url":"https://www.youtube.com/watch?v=K-ssUVyfn5g","hostname":"www.youtube.com","thumbnail":"https://i.ytimg.com/vi/K-ssUVyfn5g/maxresdefault.jpg","contentType":"media+video","platform":"youtube"},"tags":["watch-later","dftr","second-brain"],"description":"📚 Pre-order my book to get an exclusive ticket to The Feel-Good Productivity Annual Planning Workshop! https://www.feelgoodproductivity.com/?utm_campaign=bo…","createdAt":1732932833235,"updatedAt":1732932833235}